langchain_opperai/__init__.py
langchain_opperai/chat_models.py
langchain_opperai/py.typed
langchain_opperai-0.0.1.dist-info/LICENSE
langchain_opperai-0.0.1.dist-info/METADATA
langchain_opperai-0.0.1.dist-info/WHEEL
langchain_opperai-0.0.1.dist-info/RECORD
